ASMDcalculator/__init__.py
ASMDcalculator/main.py
ASMDsimpleCalculator-1.0.0.dist-info/LICENCE
ASMDsimpleCalculator-1.0.0.dist-info/METADATA
ASMDsimpleCalculator-1.0.0.dist-info/WHEEL
ASMDsimpleCalculator-1.0.0.dist-info/top_level.txt
ASMDsimpleCalculator-1.0.0.dist-info/RECORD
