Metadata-Version: 2.1
Name: ASMDsimpleCalculator
Version: 1.0.0
Summary: simple calculator
Author: Benanberg Ayoub
Author-email: Ayoub4Benanberg@gmail.com
Classifier: Programming Language :: Python :: 3
Classifier: License :: OSI Approved :: MIT License
Classifier: Operating System :: OS Independent
License-File: LICENCE
